PILSkinMC/__init__.py
PILSkinMC/poses.py
pilskinmc-1.0.1.dist-info/licenses/LICENSE
pilskinmc-1.0.1.dist-info/METADATA
pilskinmc-1.0.1.dist-info/WHEEL
pilskinmc-1.0.1.dist-info/top_level.txt
pilskinmc-1.0.1.dist-info/RECORD
