Metadata-Version: 2.4
Name: PILSkinMC
Version: 1.0.1
Summary: PILSkinMC is a basic Minecraft player skin renderer for Python's PIL (Pillow) library.
Home-page: https://github.com/SkylaDev/PILSkinMC
Author: SkylasJustVibin
License: MIT
Project-URL: Issue Tracker, https://github.com/SkylaDev/PILSkinMC/issues
Classifier: License :: OSI Approved :: MIT License
Classifier: Intended Audience :: Developers
Classifier: Natural Language :: English
Classifier: Operating System :: OS Independent
License-File: LICENSE
Requires-Dist: Pillow
Requires-Dist: numpy
Dynamic: author
Dynamic: classifier
Dynamic: description
Dynamic: description-content-type
Dynamic: home-page
Dynamic: license
Dynamic: license-file
Dynamic: project-url
Dynamic: requires-dist
Dynamic: summary
